{
  "project_info": {
    "project_number": "965672508646",
    "firebase_url": "https://deliveryapp-e145b.firebaseio.com",
    "project_id": "deliveryapp-e145b",
    "storage_bucket": "deliveryapp-e145b.appspot.com"
  },
  "client": [
    {
      "client_info": {
        "mobilesdk_app_id": "1:965672508646:android:4ff218de51a66316",
        "android_client_info": {
          "package_name": "com.rowland.delivery.merchant"
        }
      },
      "oauth_client": [
        {
          "client_id": "965672508646-7tltbij9f46043khqkn1t0dr355ulmn8.apps.googleusercontent.com",
          "client_type": 1,
          "android_info": {
            "package_name": "com.rowland.delivery.merchant",
            "certificate_hash": "76fdec27264e8fc8e4773493d23cd742f0d72ecf"
          }
        },
        {
          "client_id": "965672508646-kqasfah6o58n5hom9alfflgc355h3eci.apps.googleusercontent.com",
          "client_type": 3
        }
      ],
      "api_key": [
        {
          "current_key": "AIzaSyB1R617Lg6pVWM_fqUfit59GfIu9DwoSPQ"
        }
      ],
      "services": {
        "analytics_service": {
          "status": 1
        },
        "appinvite_service": {
          "status": 2,
          "other_platform_oauth_client": [
            {
              "client_id": "965672508646-kqasfah6o58n5hom9alfflgc355h3eci.apps.googleusercontent.com",
              "client_type": 3
            }
          ]
        },
        "ads_service": {
          "status": 2
        }
      }
    }
  ],
  "configuration_version": "1"
}